Metadata-Version: 2.0
Name: django-isomorphic
Version: 0.0.2
Summary: A Django template backend for JavaScript.
Home-page: https://github.com/wildfish/django-isomorphic
Author: Jonas Hagstedt
Author-email: jonas@wildfish.com
License: BSD License
Keywords: django isomorphic
Platform: UNKNOWN
Classifier: Development Status :: 4 - Beta
Classifier: Environment :: Web Environment
Classifier: Framework :: Django
Classifier: License :: OSI Approved :: BSD License
Classifier: Operating System :: OS Independent
Classifier: Programming Language :: Python
Classifier: Programming Language :: Python :: 2.7
Classifier: Programming Language :: Python :: 3
Classifier: Programming Language :: Python :: 3.3
Classifier: Programming Language :: Python :: 3.4
Requires-Dist: Django (>=1.8,<=1.9)
